{
  "$schema": "https://go.kicad.org/pcm/schemas/v2",
  "schema_version": 2,
  "maintainer": {
    "name": "Adam Werner",
    "contact": {
      "email": "werneradam00@gmail.com"
    }
  },
  "name": "Via Stitching repository",
  "packages": {
    "url": "https://raw.githubusercontent.com/Wadam100/via-stitching/main/packages.json",
    "sha256": "0867c2459fbda781ef326f7af20a0222530b16322bde62c90eb5925e5f5e855c",
    "update_time_utc": "2026-04-30 17:34:56",
    "update_timestamp": 1777570496
  }
}
